vocexcel-0.9.0.dist-info/METADATA
vocexcel-0.9.0.dist-info/WHEEL
vocexcel-0.9.0.dist-info/entry_points.txt
vocexcel-0.9.0.dist-info/licenses/LICENSE
vocexcel/.DS_Store
vocexcel/__init__.py
vocexcel/convert.py
vocexcel/convert_021.py
vocexcel/convert_030.py
vocexcel/convert_040.py
vocexcel/convert_043.py
vocexcel/convert_060.py
vocexcel/convert_063.py
vocexcel/convert_070.py
vocexcel/convert_071.py
vocexcel/convert_0812.py
vocexcel/convert_085.py
vocexcel/convert_gsheets.py
vocexcel/models.py
vocexcel/profiles.py
vocexcel/settings.py
vocexcel/templates/.DS_Store
vocexcel/templates/VocExcel-template-030.xlsx
vocexcel/templates/VocExcel-template-040.xlsx
vocexcel/templates/VocExcel-template-041.xlsx
vocexcel/templates/VocExcel-template-042.xlsx
vocexcel/templates/VocExcel-template-043.xlsx
vocexcel/templates/VocExcel-template-050.xlsx
vocexcel/templates/VocExcel-template-060.xlsx
vocexcel/templates/VocExcel-template-062.xlsx
vocexcel/templates/VocExcel-template-063.xlsx
vocexcel/templates/VocExcel-template-070.xlsx
vocexcel/templates/VocExcel-template-071-GA.xlsx
vocexcel/templates/VocExcel-template-071.xlsx
vocexcel/templates/VocExcel-template-0812.xlsx
vocexcel/templates/VocExcel-template-085-GA.xlsx
vocexcel/templates/VocExcel-template-085.xlsx
vocexcel/templates/VocExcel-template-090-GA.xlsx
vocexcel/templates/VocExcel-template-090.xlsx
vocexcel/utils.py
vocexcel/vocpub-5.1.ttl
vocexcel-0.9.0.dist-info/RECORD
