Metadata-Version: 2.1
Name: vocexcel
Version: 0.9.0
Summary: Another Excel to RDF converter for SKOS vocabs, but one that include profile-based validation of results.
Author-Email: Nicholas Car <nick@kurrawong.ai>
Requires-Python: <4.0.0,>=3.12
Requires-Dist: openpyxl<4.0.0,>=3.0.9
Requires-Dist: rdflib<8.0.0,>=7.5.0
Requires-Dist: pydantic>2.11
Requires-Dist: pyshacl<1.0.0,>=0.18.1
Requires-Dist: dateutils<1.0.0,>=0.6.12
Requires-Dist: colorama<1.0.0,>=0.4.4
Requires-Dist: pytest<8.0.0,>=7.2.0
Requires-Dist: setuptools<71.0.0,>=70.0.0
Requires-Dist: pipdeptree<3.0.0,>=2.3.3
Requires-Dist: jinja2<4.0.0,>=3.1.2
Requires-Dist: mangum<1.0.0,>=0.17.0
Requires-Dist: black<26.0.0,>=25.1.0
Requires-Dist: python-multipart>=0.0.20
Requires-Dist: hatch>=1.16.1
